MANIFEST.in
README.rst
demo_meg_denoising.py
demo_sample_denoising.py
demo_simu_denoising.py
meeg_tools.py
setup.cfg
setup.py
bird/__init__.py
bird/_bird.py
bird/mdct_tools.py
bird.egg-info/PKG-INFO
bird.egg-info/SOURCES.txt
bird.egg-info/dependency_links.txt
bird.egg-info/not-zip-safe
bird.egg-info/top_level.txt
bird/tests/test_bird.py
bird/tests/test_mdct_tools.py