Metadata-Version: 1.1
Name: bird
Version: 0.1
Summary: BIRD
Home-page: https://github.com/mmoussallam/bird
Author: Alexandre Gramfort
Author-email: alexandre.gramfort@telecom-paristech.fr
License: BSD (3-clause)
Download-URL: https://github.com/mmoussallam/bird
Platform: any
Classifier: Intended Audience :: Science/Research
Classifier: Intended Audience :: Developers
Classifier: License :: OSI Approved
Classifier: Programming Language :: Python
Classifier: Topic :: Software Development
Classifier: Topic :: Scientific/Engineering
Classifier: Operating System :: Microsoft :: Windows
Classifier: Operating System :: POSIX
Classifier: Operating System :: Unix
Classifier: Operating System :: MacOS
